[
  {
    "id": "c1111111-1111-1111-1111-111111111111",
    "created_by": null,
    "campaign_type": "PLATFORM",
    "status": "ACTIVE",
    "title": "Welcome to military.contractors",
    "body": "The only job board built specifically for veterans. Search by your MOS to find matched opportunities.",
    "cta_label": "Get Started",
    "cta_url": "/mos",
    "target_page": "HOME",
    "target_mos_codes": null,
    "target_company_slugs": null,
    "priority": 100,
    "max_impressions_per_session": 2,
    "budget_total_impressions": null,
    "actual_impressions": 0,
    "actual_clicks": 0,
    "starts_at": "2025-10-22T19:20:39.6049+00:00",
    "ends_at": "2026-02-19T19:20:39.6049+00:00",
    "reviewed_by": null,
    "reviewed_at": null,
    "review_notes": null,
    "created_at": "2025-11-21T19:20:39.6049+00:00",
    "updated_at": "2025-11-21T19:20:39.6049+00:00"
  },
  {
    "id": "c2222222-2222-2222-2222-222222222222",
    "created_by": null,
    "campaign_type": "JOB",
    "status": "ACTIVE",
    "title": "Cyber Roles at Booz Allen",
    "body": "Booz Allen is hiring experienced cyber professionals. TS/SCI required. Competitive salary and benefits.",
    "cta_label": "View Jobs",
    "cta_url": "/companies/booz-allen",
    "target_page": "MOS",
    "target_mos_codes": [
      "17C",
      "CTN",
      "0651"
    ],
    "target_company_slugs": null,
    "priority": 90,
    "max_impressions_per_session": 3,
    "budget_total_impressions": null,
    "actual_impressions": 0,
    "actual_clicks": 0,
    "starts_at": "2025-11-14T19:20:39.6049+00:00",
    "ends_at": "2025-12-21T19:20:39.6049+00:00",
    "reviewed_by": null,
    "reviewed_at": null,
    "review_notes": null,
    "created_at": "2025-11-21T19:20:39.6049+00:00",
    "updated_at": "2025-11-21T19:20:39.6049+00:00"
  },
  {
    "id": "c3333333-3333-3333-3333-333333333333",
    "created_by": null,
    "campaign_type": "SERVICE",
    "status": "ACTIVE",
    "title": "Security+ Boot Camp",
    "body": "Get certified in 5 days. VA-approved. Next cohort starting soon. Perfect for transitioning service members.",
    "cta_label": "Learn More",
    "cta_url": "/advertise",
    "target_page": "ANY",
    "target_mos_codes": null,
    "target_company_slugs": null,
    "priority": 80,
    "max_impressions_per_session": 2,
    "budget_total_impressions": null,
    "actual_impressions": 0,
    "actual_clicks": 0,
    "starts_at": "2025-11-07T19:20:39.6049+00:00",
    "ends_at": "2026-01-05T19:20:39.6049+00:00",
    "reviewed_by": null,
    "reviewed_at": null,
    "review_notes": null,
    "created_at": "2025-11-21T19:20:39.6049+00:00",
    "updated_at": "2025-11-21T19:20:39.6049+00:00"
  },
  {
    "id": "c4444444-4444-4444-4444-444444444444",
    "created_by": null,
    "campaign_type": "BRAND",
    "status": "ACTIVE",
    "title": "Leidos: Technology for Mission",
    "body": "Join a Fortune 500 leader in defense and intelligence. Careers across all theaters and domains.",
    "cta_label": "Explore Careers",
    "cta_url": "/companies/leidos",
    "target_page": "ANY",
    "target_mos_codes": null,
    "target_company_slugs": null,
    "priority": 70,
    "max_impressions_per_session": 3,
    "budget_total_impressions": null,
    "actual_impressions": 0,
    "actual_clicks": 0,
    "starts_at": "2025-11-01T19:20:39.6049+00:00",
    "ends_at": "2026-01-20T19:20:39.6049+00:00",
    "reviewed_by": null,
    "reviewed_at": null,
    "review_notes": null,
    "created_at": "2025-11-21T19:20:39.6049+00:00",
    "updated_at": "2025-11-21T19:20:39.6049+00:00"
  },
  {
    "id": "79e32f0d-8701-4546-999c-c68b3e710061",
    "created_by": "32d65899-aee9-4133-bef1-aa0f16ac5546",
    "campaign_type": "JOB",
    "status": "PENDING_REVIEW",
    "title": "Network Engineer - Lead",
    "body": "AEO Digital LLC is seeking a senior Network Engineer with serious AI skills.",
    "cta_label": "Apply Here",
    "cta_url": "https://aeodigital.com/jobs/342544",
    "target_page": "MOS",
    "target_mos_codes": null,
    "target_company_slugs": null,
    "priority": 5,
    "max_impressions_per_session": 9,
    "budget_total_impressions": null,
    "actual_impressions": 0,
    "actual_clicks": 0,
    "starts_at": "2025-11-22T00:00:00+00:00",
    "ends_at": "2025-11-29T00:00:00+00:00",
    "reviewed_by": null,
    "reviewed_at": null,
    "review_notes": null,
    "created_at": "2025-11-22T08:26:43.600252+00:00",
    "updated_at": "2025-11-22T08:26:43.600252+00:00"
  },
  {
    "id": "6eba05ea-8e8e-45f2-ad8c-59813e9d923d",
    "created_by": "32d65899-aee9-4133-bef1-aa0f16ac5546",
    "campaign_type": "JOB",
    "status": "PENDING_REVIEW",
    "title": "Network Engineer",
    "body": "AEO Digital LLC is seeking a Senior Network Engineer with AI prompting experience.",
    "cta_label": "Apply Here",
    "cta_url": "https://aeodigital.com/jobs1234",
    "target_page": "MOS",
    "target_mos_codes": null,
    "target_company_slugs": null,
    "priority": 5,
    "max_impressions_per_session": 9,
    "budget_total_impressions": null,
    "actual_impressions": 0,
    "actual_clicks": 0,
    "starts_at": "2025-11-22T00:00:00+00:00",
    "ends_at": "2025-11-29T00:00:00+00:00",
    "reviewed_by": null,
    "reviewed_at": null,
    "review_notes": null,
    "created_at": "2025-11-22T15:41:25.624541+00:00",
    "updated_at": "2025-11-22T15:41:25.624541+00:00"
  },
  {
    "id": "89acc0ce-4104-4b0c-ab9f-e96d3b6b078c",
    "created_by": "32d65899-aee9-4133-bef1-aa0f16ac5546",
    "campaign_type": "JOB",
    "status": "PENDING_REVIEW",
    "title": "Network Engineer -Lead",
    "body": "AEO Digital LLC is seeking a Senior Network Engineer with AI skills.",
    "cta_label": "Apply Here",
    "cta_url": "https://aeodigital.com/jobs/23343",
    "target_page": "MOS",
    "target_mos_codes": null,
    "target_company_slugs": null,
    "priority": 5,
    "max_impressions_per_session": 9,
    "budget_total_impressions": null,
    "actual_impressions": 0,
    "actual_clicks": 0,
    "starts_at": "2025-11-22T00:00:00+00:00",
    "ends_at": "2025-11-29T00:00:00+00:00",
    "reviewed_by": null,
    "reviewed_at": null,
    "review_notes": null,
    "created_at": "2025-11-22T17:44:43.024035+00:00",
    "updated_at": "2025-11-22T17:44:43.024035+00:00"
  },
  {
    "id": "5d4b2ac1-7194-451a-88a1-d5f0923131fb",
    "created_by": "32d65899-aee9-4133-bef1-aa0f16ac5546",
    "campaign_type": "JOB",
    "status": "PENDING_REVIEW",
    "title": "Network Engineer - Lead",
    "body": "AEO Digital LLC is seeking a senior Network Engineer with an advanced AI skill set.",
    "cta_label": "Apply Here",
    "cta_url": "https://aeodigital.com/jobs/133434",
    "target_page": "MOS",
    "target_mos_codes": null,
    "target_company_slugs": null,
    "priority": 5,
    "max_impressions_per_session": 9,
    "budget_total_impressions": null,
    "actual_impressions": 0,
    "actual_clicks": 0,
    "starts_at": "2025-11-21T00:00:00+00:00",
    "ends_at": "2025-11-28T00:00:00+00:00",
    "reviewed_by": null,
    "reviewed_at": null,
    "review_notes": null,
    "created_at": "2025-11-22T00:33:41.391968+00:00",
    "updated_at": "2025-11-22T18:07:09.208236+00:00"
  },
  {
    "id": "ab6c80ed-3496-4c87-b03b-a40b54e88f53",
    "created_by": "32d65899-aee9-4133-bef1-aa0f16ac5546",
    "campaign_type": "JOB",
    "status": "PENDING_REVIEW",
    "title": "Systems Engineer",
    "body": "AEO Digital LLC is seeking a well rounded Systems Engineer",
    "cta_label": "Apply Now",
    "cta_url": "https://aeodigital.com/jobs/13423",
    "target_page": "MOS",
    "target_mos_codes": null,
    "target_company_slugs": null,
    "priority": 5,
    "max_impressions_per_session": 9,
    "budget_total_impressions": null,
    "actual_impressions": 0,
    "actual_clicks": 0,
    "starts_at": "2025-11-22T00:00:00+00:00",
    "ends_at": "2025-11-29T00:00:00+00:00",
    "reviewed_by": null,
    "reviewed_at": null,
    "review_notes": null,
    "created_at": "2025-11-22T19:17:29.06408+00:00",
    "updated_at": "2025-11-22T19:17:29.06408+00:00"
  },
  {
    "id": "786a7802-97d4-4560-b533-f47eaf4d9993",
    "created_by": "32d65899-aee9-4133-bef1-aa0f16ac5546",
    "campaign_type": "JOB",
    "status": "APPROVED",
    "title": "Network Engineer - Lead",
    "body": "AEO Digital LLC is seeking a senior Network Engineer with serious AI skills.",
    "cta_label": "Apply Here",
    "cta_url": "https://aeodigital.com/jobs/234342",
    "target_page": "ANY",
    "target_mos_codes": null,
    "target_company_slugs": null,
    "priority": 5,
    "max_impressions_per_session": 9,
    "budget_total_impressions": null,
    "actual_impressions": 0,
    "actual_clicks": 0,
    "starts_at": "2025-11-22T00:00:00+00:00",
    "ends_at": "2025-11-29T00:00:00+00:00",
    "reviewed_by": null,
    "reviewed_at": "2025-11-22T19:20:36.764+00:00",
    "review_notes": null,
    "created_at": "2025-11-22T08:29:44.121915+00:00",
    "updated_at": "2025-11-22T19:20:37.113559+00:00"
  },
  {
    "id": "ae959484-3839-4624-9ff7-09fd995bd28f",
    "created_by": "32d65899-aee9-4133-bef1-aa0f16ac5546",
    "campaign_type": "JOB",
    "status": "REJECTED",
    "title": "Network Engineer - Lead",
    "body": "AEO Digital LLC is seeking a senior Network Engineer with an advanced AI skill set.",
    "cta_label": "Apply Here",
    "cta_url": "https://aeodigital.com/jobs/132343",
    "target_page": "ANY",
    "target_mos_codes": null,
    "target_company_slugs": null,
    "priority": 5,
    "max_impressions_per_session": 9,
    "budget_total_impressions": null,
    "actual_impressions": 0,
    "actual_clicks": 0,
    "starts_at": "2025-11-21T00:00:00+00:00",
    "ends_at": "2025-11-28T00:00:00+00:00",
    "reviewed_by": null,
    "reviewed_at": "2025-11-22T22:08:19.189+00:00",
    "review_notes": null,
    "created_at": "2025-11-21T21:37:56.169377+00:00",
    "updated_at": "2025-11-22T22:08:19.346922+00:00"
  },
  {
    "id": "d88b2d24-c333-4a7f-9427-57a32321cc0c",
    "created_by": null,
    "campaign_type": "JOB",
    "status": "ACTIVE",
    "title": "Hiring Signal Vets for Kuwait",
    "body": "KBR is looking for 25B/25U veterans for IT support roles in Camp Arifjan. Secret clearance required.",
    "cta_label": "View Roles",
    "cta_url": "/companies/kbr",
    "target_page": "MOS",
    "target_mos_codes": [
      "25B",
      "25U",
      "25Q",
      "25S"
    ],
    "target_company_slugs": [],
    "priority": 10,
    "max_impressions_per_session": 3,
    "budget_total_impressions": 10000,
    "actual_impressions": 0,
    "actual_clicks": 0,
    "starts_at": "2025-12-08T19:30:00.242838+00:00",
    "ends_at": "2026-03-08T19:30:00.242846+00:00",
    "reviewed_by": null,
    "reviewed_at": null,
    "review_notes": null,
    "created_at": "2025-12-08T19:30:05.400758+00:00",
    "updated_at": "2025-12-08T19:30:05.400758+00:00"
  },
  {
    "id": "1739ebf3-9ce3-4e6c-9f2e-2fe9e03c6e71",
    "created_by": null,
    "campaign_type": "SERVICE",
    "status": "ACTIVE",
    "title": "Resume Help for Contractors",
    "body": "Struggling to translate your MOS? Get a free resume review from our veteran transition experts.",
    "cta_label": "Learn More",
    "cta_url": "/about",
    "target_page": "COMPANY",
    "target_mos_codes": [],
    "target_company_slugs": [
      "amentum",
      "kbr",
      "leidos"
    ],
    "priority": 5,
    "max_impressions_per_session": 2,
    "budget_total_impressions": 5000,
    "actual_impressions": 0,
    "actual_clicks": 0,
    "starts_at": "2025-12-08T19:30:00.242852+00:00",
    "ends_at": "2026-02-06T19:30:00.242852+00:00",
    "reviewed_by": null,
    "reviewed_at": null,
    "review_notes": null,
    "created_at": "2025-12-08T19:30:05.519551+00:00",
    "updated_at": "2025-12-08T19:30:05.519551+00:00"
  },
  {
    "id": "e4e53596-8e52-4b15-aeba-fc3739cd60da",
    "created_by": null,
    "campaign_type": "JOB",
    "status": "ACTIVE",
    "title": "Featured: Senior Network Engineer",
    "body": "Leidos is hiring for a top-tier OCONUS contract. $140k+, TS/SCI required.",
    "cta_label": "View Job",
    "cta_url": "/jobs",
    "target_page": "HOME",
    "target_mos_codes": [],
    "target_company_slugs": [],
    "priority": 8,
    "max_impressions_per_session": 3,
    "budget_total_impressions": 15000,
    "actual_impressions": 0,
    "actual_clicks": 0,
    "starts_at": "2025-12-08T19:30:00.242854+00:00",
    "ends_at": "2026-01-07T19:30:00.242855+00:00",
    "reviewed_by": null,
    "reviewed_at": null,
    "review_notes": null,
    "created_at": "2025-12-08T19:30:05.604279+00:00",
    "updated_at": "2025-12-08T19:30:05.604279+00:00"
  },
  {
    "id": "2225bf4f-d935-4088-a6b2-1a514d67bc52",
    "created_by": null,
    "campaign_type": "SERVICE",
    "status": "ACTIVE",
    "title": "CompTIA Security+ Training",
    "body": "Most contractor roles require Security+. Get certified in 2 weeks with our veteran bootcamp.",
    "cta_label": "Get Certified",
    "cta_url": "/about",
    "target_page": "MOS",
    "target_mos_codes": [],
    "target_company_slugs": [],
    "priority": 4,
    "max_impressions_per_session": 2,
    "budget_total_impressions": 8000,
    "actual_impressions": 0,
    "actual_clicks": 0,
    "starts_at": "2025-12-08T19:30:00.242857+00:00",
    "ends_at": "2026-04-07T19:30:00.242858+00:00",
    "reviewed_by": null,
    "reviewed_at": null,
    "review_notes": null,
    "created_at": "2025-12-08T19:30:05.69228+00:00",
    "updated_at": "2025-12-08T19:30:05.69228+00:00"
  },
  {
    "id": "f6eb3908-ce8c-4ac9-9927-752ddc5f5b2b",
    "created_by": null,
    "campaign_type": "BRAND",
    "status": "ACTIVE",
    "title": "Why choose Leidos?",
    "body": "Looking for a change? Leidos offers top-tier benefits and OCONUS rotation options.",
    "cta_label": "See Careers",
    "cta_url": "/companies/leidos",
    "target_page": "COMPANY",
    "target_mos_codes": [],
    "target_company_slugs": [
      "general-dynamics",
      "booz-allen"
    ],
    "priority": 9,
    "max_impressions_per_session": 2,
    "budget_total_impressions": 5000,
    "actual_impressions": 0,
    "actual_clicks": 0,
    "starts_at": "2025-12-08T19:30:00.242859+00:00",
    "ends_at": "2026-01-22T19:30:00.24286+00:00",
    "reviewed_by": null,
    "reviewed_at": null,
    "review_notes": null,
    "created_at": "2025-12-08T19:30:05.829647+00:00",
    "updated_at": "2025-12-08T19:30:05.829647+00:00"
  },
  {
    "id": "927737d7-e5a6-4739-ad3f-c0fc220d5648",
    "created_by": null,
    "campaign_type": "JOB",
    "status": "ACTIVE",
    "title": "Security Forces: Qatar",
    "body": "Looking for 11B/0311 veterans for static security and force protection roles in Qatar.",
    "cta_label": "Apply Now",
    "cta_url": "/jobs",
    "target_page": "MOS",
    "target_mos_codes": [
      "11B",
      "0311",
      "11C"
    ],
    "target_company_slugs": [],
    "priority": 10,
    "max_impressions_per_session": 3,
    "budget_total_impressions": 8000,
    "actual_impressions": 0,
    "actual_clicks": 0,
    "starts_at": "2025-12-08T19:30:00.242862+00:00",
    "ends_at": "2026-02-06T19:30:00.242863+00:00",
    "reviewed_by": null,
    "reviewed_at": null,
    "review_notes": null,
    "created_at": "2025-12-08T19:30:05.993336+00:00",
    "updated_at": "2025-12-08T19:30:05.993336+00:00"
  },
  {
    "id": "a8b89b21-8acc-4b32-8f76-7fa88580843c",
    "created_by": null,
    "campaign_type": "PLATFORM",
    "status": "ACTIVE",
    "title": "Create Your Profile",
    "body": "Create a profile today and let recruiters from Amentum, KBR, and Leidos find you.",
    "cta_label": "Get Started",
    "cta_url": "/dashboard",
    "target_page": "HOME",
    "target_mos_codes": [],
    "target_company_slugs": [],
    "priority": 6,
    "max_impressions_per_session": 2,
    "budget_total_impressions": 20000,
    "actual_impressions": 0,
    "actual_clicks": 0,
    "starts_at": "2025-12-08T19:30:00.242864+00:00",
    "ends_at": null,
    "reviewed_by": null,
    "reviewed_at": null,
    "review_notes": null,
    "created_at": "2025-12-08T19:30:06.08402+00:00",
    "updated_at": "2025-12-08T19:30:06.08402+00:00"
  }
]